deoldify/__init__.py
deoldify/_device.py
deoldify/augs.py
deoldify/critics.py
deoldify/dataset.py
deoldify/device_id.py
deoldify/filters.py
deoldify/generators.py
deoldify/layers.py
deoldify/loss.py
deoldify/save.py
deoldify/unet.py
deoldify/visualize.py
fastai/__init__.py
fastai/basic_data.py
fastai/basic_train.py
fastai/basics.py
fastai/callback.py
fastai/collab.py
fastai/core.py
fastai/data_block.py
fastai/datasets.py
fastai/distributed.py
fastai/general_optimizer.py
fastai/launch.py
fastai/layers.py
fastai/metrics.py
fastai/script.py
fastai/sixel.py
fastai/torch_core.py
fastai/train.py
fastai/version.py
fastai/callbacks/__init__.py
fastai/callbacks/csv_logger.py
fastai/callbacks/fp16.py
fastai/callbacks/general_sched.py
fastai/callbacks/hooks.py
fastai/callbacks/loss_metrics.py
fastai/callbacks/lr_finder.py
fastai/callbacks/mem.py
fastai/callbacks/misc.py
fastai/callbacks/mixup.py
fastai/callbacks/mlflow.py
fastai/callbacks/one_cycle.py
fastai/callbacks/oversampling.py
fastai/callbacks/rnn.py
fastai/callbacks/tensorboard.py
fastai/callbacks/tracker.py
fastai/gen_doc/__init__.py
fastai/gen_doc/convert2html.py
fastai/gen_doc/core.py
fastai/gen_doc/docstrings.py
fastai/gen_doc/doctest.py
fastai/gen_doc/gen_notebooks.py
fastai/gen_doc/nbdoc.py
fastai/gen_doc/nbtest.py
fastai/imports/__init__.py
fastai/imports/core.py
fastai/imports/torch.py
fastai/tabular/__init__.py
fastai/tabular/data.py
fastai/tabular/models.py
fastai/tabular/transform.py
fastai/text/__init__.py
fastai/text/data.py
fastai/text/interpret.py
fastai/text/learner.py
fastai/text/transform.py
fastai/text/models/__init__.py
fastai/text/models/awd_lstm.py
fastai/text/models/qrnn.py
fastai/text/models/transformer.py
fastai/utils/__init__.py
fastai/utils/check_perf.py
fastai/utils/collect_env.py
fastai/utils/ipython.py
fastai/utils/mem.py
fastai/utils/mod_display.py
fastai/utils/pynvml_gate.py
fastai/utils/show_install.py
fastai/vision/__init__.py
fastai/vision/cyclegan.py
fastai/vision/data.py
deoldify-0.0.1.dist-info/LICENSE
deoldify-0.0.1.dist-info/METADATA
deoldify-0.0.1.dist-info/WHEEL
deoldify-0.0.1.dist-info/top_level.txt
deoldify-0.0.1.dist-info/RECORD
