Metadata-Version: 2.1
Name: deoldify
Version: 0.0.1
Summary: Deep Learning library for colorizing and restoring old images and video
Home-page: https://github.com/leonelhs/DeOldify
Author: Jason Antic
Author-email: sa169@gmail.com
License: MIT License
Classifier: Development Status :: 4 - Beta
Classifier: Framework :: Jupyter
Classifier: Intended Audience :: Developers
Classifier: Intended Audience :: Science/Research
Classifier: License :: OSI Approved :: MIT License
Classifier: Programming Language :: Python :: 3.6
Classifier: Programming Language :: Python :: 3.7
Classifier: Topic :: Scientific/Engineering :: Artificial Intelligence
Classifier: Topic :: Software Development :: Libraries :: Python Modules
Requires-Python: >=3.6
License-File: LICENSE
Requires-Dist: wandb
Requires-Dist: tensorboardX (>=1.6)
Requires-Dist: ffmpeg
Requires-Dist: ffmpeg-python
Requires-Dist: yt-dlp
Requires-Dist: jupyterlab
Requires-Dist: opencv-python (>=4.2.0.32)
Requires-Dist: Pillow (>=9.5.0)
Requires-Dist: torch (>=2.0.0)
Requires-Dist: torchvision
Requires-Dist: ipywidgets
